Metadata-Version: 2.1
Name: qwertyuiop-porsevati
Version: 0.0.1
Summary: my package
Home-page: UNKNOWN
Author: PorsevaTatyana
Author-email: tporseva@inbox.ru
License: UNKNOWN
Platform: UNKNOWN
